Metadata-Version: 2.1
Name: fluidCube
Version: 0.1.2
Summary: fluidCube
Home-page: https://github.com/Spektoruk3/PAK
Author: Leshin Vladimir, Spektoruk Ilya, Krukovskiy Vasiliy
Author-email: i.spektoruk@g.nsu.ru
